examples/n_dff/n_dff.v
// A sequential logic example

module dff_negedge (D, clock, Q, Qbar);
	input D, clock;
	output reg Q, Qbar;

	always @(negedge clock)
		begin
			Q = D;
			Qbar = ~D;
		end
endmodule

examples/n_dff/n_dff_tb.v
// Test bench for negative edge D flip-flop

module dff_n_test;
	reg d,clk=0;
	wire q,qbar;
	dff_negedge DUT (.D(d), .clock(clk), .Q(q), .Qbar(qbar));
	always #10 clk = ~clk;

	initial
		begin
			$dumpfile ("neg_dff.vcd");
			$dumpvars (0, dff_n_test);
			$monitor ($time, "d=%b, clk=%b, q=%b, qbar=%b", d,clk,q,qbar);
			#5 d=1'b0;
			#5 d=1'b1;
			#5 d=1'b1;
			#5 d=1'b1;
			#5 d=1'b0;
			#5 d=1'b0;
			#5 d=1'b1;
			#5 d=1'b1;
			#5 d=1'b0;
			#5 d=1'b1;
			#5 d=1'b0;
			#5 d=1'b1;
			#5 d=1'b1;
			#5 d=1'b0;
			#5 d=1'b0;
			#5 d=1'b0;
			#5 d=1'b0;
			#5 d=1'b0;
			#5 d=1'b0;
			#5 d=1'b0;
			#5 d=1'b0;
			#5 d=1'b0;
			#5 d=1'b1;
			#5 d=1'b0;
			#5 d=1'b0;
			#5 d=1'b0;
			#5 d=1'b1;
			#5 d=1'b0;
			#5 d=1'b1;
			#5 d=1'b1;
			#5 d=1'b0;
			#5 d=1'b0;
			#5 d=1'b0;
			#5 d=1'b1;
			#5 d=1'b0;
			#5$finish;
		end
endmodule

examples/n_dff/neg_dff.vcd
$date
	Thu Dec  8 11:31:58 2022
$end
$version
	Icarus Verilog
$end
$timescale
	1s
$end
$scope module dff_n_test $end
$var wire 1 ! qbar $end
$var wire 1 " q $end
$var reg 1 # clk $end
$var reg 1 $ d $end
$scope module DUT $end
$var wire 1 $ D $end
$var wire 1 # clock $end
$var reg 1 " Q $end
$var reg 1 ! Qbar $end
$upscope $end
$upscope $end
$enddefinitions $end
#0
$dumpvars
x$
0#
x"
x!
$end
#5
0$
#10
1$
1#
#20
0!
1"
0#
#25
0$
#30
1#
#35
1$
#40
0#
#45
0$
#50
1$
1#
#55
0$
#60
1$
0#
#70
0$
1#
#80
1!
0"
0#
#90
1#
#100
0#
#110
1#
#115
1$
#120
0$
0#
#130
1#
#135
1$
#140
0$
0#
#145
1$
#150
1#
#155
0$
#160
0#
#170
1$
1#
#175
0$
