examples/delay/module_d.v
// Define a simple combination module called D
module D (out, a, b, c);

	// I/O port declarations
	output out;
	input a,b,c;

	// Internal nets
	wire e;

	// Instantiate primitive gates to build the circuit
	and #(5) a1(e, a, b); // Delay of 5 on gate a1
	or #(4) o1(out, e, c); // Delay of 4 on gate o1

endmodule

examples/delay/module_d_tb.v
// Stimulus (top-level module)
module stimulus;
	
	// Declare variables
	reg A, B, C;
	wire OUT;

	// Instantiate the module D
	D d1 (OUT, A, B, C);

	// Stimulate the inputs. Finish the simulation at 40 time units.
	initial
	begin
		$dumpfile ("module_d.vcd");
		$dumpvars (0, stimulus);
		A= 1'b0; B= 1'b0; C= 1'b0;
		#10 A= 1'b1; B= 1'b1; C= 1'b1;

		#10 A= 1'b1; B= 1'b0; C= 1'b0;

		#20 $finish;
	end
endmodule

examples/delay/module_d.vcd
$date
	Sat Jan 14 20:31:19 2023
$end
$version
	Icarus Verilog
$end
$timescale
	1s
$end
$scope module stimulus $end
$var wire 1 ! OUT $end
$var reg 1 " A $end
$var reg 1 # B $end
$var reg 1 $ C $end
$scope module d1 $end
$var wire 1 " a $end
$var wire 1 # b $end
$var wire 1 $ c $end
$var wire 1 % e $end
$var wire 1 ! out $end
$upscope $end
$upscope $end
$enddefinitions $end
#0
$dumpvars
x%
0$
0#
0"
x!
$end
#5
0%
#9
0!
#10
1$
1#
1"
#14
1!
#15
1%
#20
0$
0#
#25
0%
#29
0!
